prcli/__init__.py
prcli/pricerunner_cli.py
pricerunner_cli-0.2.0.dist-info/LICENSE
pricerunner_cli-0.2.0.dist-info/METADATA
pricerunner_cli-0.2.0.dist-info/WHEEL
pricerunner_cli-0.2.0.dist-info/entry_points.txt
pricerunner_cli-0.2.0.dist-info/top_level.txt
pricerunner_cli-0.2.0.dist-info/RECORD
